llmevaluator/__init__.py
llmevaluator/evaluators.py
llmevaluator/file_handler.py
llmevaluator/main.py
llmevaluator/metrics.py
llmevaluator-0.1.0.dist-info/LICENSE
llmevaluator-0.1.0.dist-info/METADATA
llmevaluator-0.1.0.dist-info/WHEEL
llmevaluator-0.1.0.dist-info/top_level.txt
llmevaluator-0.1.0.dist-info/RECORD
