Metadata-Version: 2.1
Name: llmevaluator
Version: 0.1.0
Summary: A package for evaluating text files.
Author: Turing Generative A.I Team
Author-email: leonard.b-c@turing.com
License: MIT
License-File: LICENSE
Requires-Dist: absl-py ==2.1.0
Requires-Dist: aiohttp ==3.9.5
Requires-Dist: aiosignal ==1.3.1
Requires-Dist: annotated-types ==0.6.0
Requires-Dist: anyio ==4.3.0
Requires-Dist: appdirs ==1.4.4
Requires-Dist: attrs ==23.2.0
Requires-Dist: bert-score ==0.3.13
Requires-Dist: certifi ==2024.2.2
Requires-Dist: charset-normalizer ==3.3.2
Requires-Dist: click ==8.1.7
Requires-Dist: colorama ==0.4.6
Requires-Dist: contourpy ==1.2.1
Requires-Dist: cycler ==0.12.1
Requires-Dist: dataclasses-json ==0.6.4
Requires-Dist: datasets ==2.19.0
Requires-Dist: deepeval ==0.21.34
Requires-Dist: dill ==0.3.8
Requires-Dist: distro ==1.9.0
Requires-Dist: docx2txt ==0.8
Requires-Dist: execnet ==2.1.1
Requires-Dist: filelock ==3.13.4
Requires-Dist: fonttools ==4.51.0
Requires-Dist: frozenlist ==1.4.1
Requires-Dist: fsspec ==2024.3.1
Requires-Dist: greenlet ==3.0.3
Requires-Dist: h11 ==0.14.0
Requires-Dist: httpcore ==1.0.5
Requires-Dist: httpx ==0.27.0
Requires-Dist: huggingface-hub ==0.22.2
Requires-Dist: idna ==3.7
Requires-Dist: importlib-metadata ==7.0.2
Requires-Dist: iniconfig ==2.0.0
Requires-Dist: intel-openmp ==2021.4.0
Requires-Dist: Jinja2 ==3.1.3
Requires-Dist: joblib ==1.4.0
Requires-Dist: jsonpatch ==1.33
Requires-Dist: jsonpointer ==2.4
Requires-Dist: kiwisolver ==1.4.5
Requires-Dist: langchain ==0.1.16
Requires-Dist: langchain-community ==0.0.34
Requires-Dist: langchain-core ==0.1.46
Requires-Dist: langchain-openai ==0.1.3
Requires-Dist: langchain-text-splitters ==0.0.1
Requires-Dist: langsmith ==0.1.51
Requires-Dist: markdown-it-py ==3.0.0
Requires-Dist: MarkupSafe ==2.1.5
Requires-Dist: marshmallow ==3.21.1
Requires-Dist: matplotlib ==3.8.4
Requires-Dist: mdurl ==0.1.2
Requires-Dist: mkl ==2021.4.0
Requires-Dist: moverscore ==0.96
Requires-Dist: mpmath ==1.3.0
Requires-Dist: multidict ==6.0.5
Requires-Dist: multiprocess ==0.70.16
Requires-Dist: mypy-extensions ==1.0.0
Requires-Dist: nest-asyncio ==1.6.0
Requires-Dist: networkx ==3.3
Requires-Dist: nltk ==3.8.1
Requires-Dist: numpy ==1.26.4
Requires-Dist: openai ==1.23.6
Requires-Dist: orjson ==3.10.1
Requires-Dist: packaging ==23.2
Requires-Dist: pandas ==2.2.2
Requires-Dist: pillow ==10.3.0
Requires-Dist: pluggy ==1.5.0
Requires-Dist: portalocker ==2.8.2
Requires-Dist: protobuf ==4.25.1
Requires-Dist: pyarrow ==16.0.0
Requires-Dist: pyarrow-hotfix ==0.6
Requires-Dist: pydantic ==2.7.1
Requires-Dist: pydantic-core ==2.18.2
Requires-Dist: pyemd ==1.0.0
Requires-Dist: Pygments ==2.17.2
Requires-Dist: pyparsing ==3.1.2
Requires-Dist: pysbd ==0.3.4
Requires-Dist: pytest ==8.1.1
Requires-Dist: pytest-repeat ==0.9.3
Requires-Dist: pytest-xdist ==3.5.0
Requires-Dist: python-dateutil ==2.9.0.post0
Requires-Dist: python-dotenv ==1.0.1
Requires-Dist: pytz ==2024.1
Requires-Dist: pywin32 ==306
Requires-Dist: PyYAML ==6.0.1
Requires-Dist: ragas ==0.1.7
Requires-Dist: regex ==2024.4.16
Requires-Dist: requests ==2.31.0
Requires-Dist: rich ==13.7.1
Requires-Dist: rouge-score ==0.1.2
Requires-Dist: safetensors ==0.4.3
Requires-Dist: sentry-sdk ==2.0.1
Requires-Dist: shellingham ==1.5.4
Requires-Dist: six ==1.16.0
Requires-Dist: sniffio ==1.3.1
Requires-Dist: SQLAlchemy ==2.0.29
Requires-Dist: sympy ==1.12
Requires-Dist: tabulate ==0.9.0
Requires-Dist: tbb ==2021.12.0
Requires-Dist: tenacity ==8.2.3
Requires-Dist: tiktoken ==0.6.0
Requires-Dist: tokenizers ==0.19.1
Requires-Dist: torch ==2.3.0
Requires-Dist: tqdm ==4.66.2
Requires-Dist: transformers ==4.40.1
Requires-Dist: typer ==0.12.3
Requires-Dist: typing ==3.7.4.3
Requires-Dist: typing-inspect ==0.9.0
Requires-Dist: typing-extensions ==4.11.0
Requires-Dist: tzdata ==2024.1
Requires-Dist: urllib3 ==2.2.1
Requires-Dist: xxhash ==3.4.1
Requires-Dist: yarl ==1.9.4
Requires-Dist: zipp ==3.18.1
